examples/__init__.py
examples/example.py
pyerail/__init__.py
pyerail/helpers.py
pyerail/pyerail.py
pyerail-0.2.1.dist-info/DESCRIPTION.rst
pyerail-0.2.1.dist-info/METADATA
pyerail-0.2.1.dist-info/RECORD
pyerail-0.2.1.dist-info/WHEEL
pyerail-0.2.1.dist-info/metadata.json
pyerail-0.2.1.dist-info/top_level.txt
