Metadata-Version: 2.0
Name: pyerail
Version: 0.2.1
Summary: Python wrapper for eRail API.
Home-page: https://github.com/aksbuzz/PyeRail
Author: Akshay
Author-email: akshayjr69@gmail.com
License: Copyright (c) 2017, Akshay.
